djangocms_redirect/__init__.py
djangocms_redirect/admin.py
djangocms_redirect/middleware.py
djangocms_redirect/models.py
djangocms_redirect/utils.py
djangocms_redirect/locale/en/LC_MESSAGES/django.po
djangocms_redirect/migrations/0001_initial.py
djangocms_redirect/migrations/0002_auto_20170321_1807.py
djangocms_redirect/migrations/0003_auto_20190810_1009.py
djangocms_redirect/migrations/__init__.py
djangocms_redirect-0.7.3.dist-info/LICENSE
djangocms_redirect-0.7.3.dist-info/METADATA
djangocms_redirect-0.7.3.dist-info/WHEEL
djangocms_redirect-0.7.3.dist-info/top_level.txt
djangocms_redirect-0.7.3.dist-info/RECORD
