Metadata-Version: 2.2
Name: djangocms-redirect
Version: 0.7.3
Summary: A django CMS enabled application to handle redirects
Home-page: https://github.com/nephila/djangocms-redirect
Author: Iacopo Spalletti
Author-email: i.spalletti@nephila.it
License: BSD
Project-URL: Documentation, https://djangocms-redirect.readthedocs.io/
Classifier: License :: OSI Approved :: BSD License
Classifier: Development Status :: 5 - Production/Stable
Classifier: Framework :: Django
Classifier: Framework :: Django :: 3.2
Classifier: Framework :: Django :: 4.1
Classifier: Framework :: Django :: 4.2
Classifier: Programming Language :: Python
Classifier: Programming Language :: Python :: 3
Classifier: Programming Language :: Python :: 3.9
Classifier: Programming Language :: Python :: 3.10
Classifier: Programming Language :: Python :: 3.11
Requires-Python: >=3.6
License-File: LICENSE
Requires-Dist: django-cms>=3.9
Provides-Extra: docs
Requires-Dist: django<5; extra == "docs"
